[{"id":"fb1f9786.895398","type":"tab","label":"text to speech","disabled":false,"info":""},{"id":"dccaef2b.e17e","type":"comment","z":"fb1f9786.895398","name":"TTS - Text to Speech Demo","info":"","x":300,"y":80,"wires":[]},{"id":"390cfb7a.2d0bf4","type":"ui_audio","z":"fb1f9786.895398","name":"Audio Output","group":"1060b50f.fefd2b","voice":"en-US","always":"","x":530,"y":80,"wires":[]},{"id":"f98e7e38.96a28","type":"ui_text_input","z":"fb1f9786.895398","name":"taking input text","label":"","tooltip":"","group":"1060b50f.fefd2b","order":9,"width":0,"height":0,"passthru":true,"mode":"text","delay":"0","topic":"","x":320,"y":140,"wires":[["390cfb7a.2d0bf4","ea205b0f.f6d678","6c4c64e6.31282c"]]},{"id":"1d4171bc.69e78e","type":"inject","z":"fb1f9786.895398","name":"","props":[{"p":"payload","v":"Hello","vt":"str"},{"p":"topic","v":"Hello","vt":"string"}],"repeat":"","crontab":"","once":false,"onceDelay":0.1,"topic":"Hello","payload":"Hello","payloadType":"str","x":120,"y":160,"wires":[["f98e7e38.96a28"]]},{"id":"70916729.4ba428","type":"ui_text","z":"fb1f9786.895398","group":"1060b50f.fefd2b","order":2,"width":0,"height":0,"name":"","label":"","format":"{{msg.payload}}","layout":"row-center","x":670,"y":160,"wires":[]},{"id":"ea205b0f.f6d678","type":"delay","z":"fb1f9786.895398","name":"","pauseType":"delay","timeout":"50","timeoutUnits":"milliseconds","rate":"1","nbRateUnits":"1","rateUnits":"second","randomFirst":"1","randomLast":"5","randomUnits":"seconds","drop":false,"x":430,"y":220,"wires":[["f4a28adc.3354a8"]]},{"id":"f4a28adc.3354a8","type":"function","z":"fb1f9786.895398","name":"Check Text","func":"text=msg.payload;\nif(text !== \"\"){\n    msg.payload = \"\";\n    return msg;\n}","outputs":1,"noerr":0,"initialize":"","finalize":"","x":210,"y":220,"wires":[["f98e7e38.96a28"]]},{"id":"6c4c64e6.31282c","type":"function","z":"fb1f9786.895398","name":"Check Text","func":"text=msg.payload;\nif(text !== \"\"){\n    msg.payload = text;\n    return msg;\n}","outputs":1,"noerr":0,"initialize":"","finalize":"","x":510,"y":160,"wires":[["70916729.4ba428"]]},{"id":"aaf63a64.863a28","type":"ui_button","z":"fb1f9786.895398","name":"","group":"1060b50f.fefd2b","order":3,"width":"6","height":"1","passthru":true,"label":"Hello.","tooltip":"","color":"","bgcolor":"","icon":"","payload":"Hello.","payloadType":"str","topic":"","x":290,"y":280,"wires":[["67f2a543.293ebc"]]},{"id":"67f2a543.293ebc","type":"link out","z":"fb1f9786.895398","name":"text out","links":["a118c2d8.975e"],"x":475,"y":280,"wires":[]},{"id":"a118c2d8.975e","type":"link in","z":"fb1f9786.895398","name":"","links":["1cf0335d.deb22d","29948579.8865fa","48ad5509.c3b53c","67f2a543.293ebc","ab49a76b.93dd58","cb4c72a6.82b3"],"x":135,"y":100,"wires":[["f98e7e38.96a28"]]},{"id":"9dfe8eb6.8b165","type":"inject","z":"fb1f9786.895398","name":"","repeat":"","crontab":"","once":false,"onceDelay":0.1,"topic":"","payload":"","payloadType":"date","x":120,"y":280,"wires":[["aaf63a64.863a28"]]},{"id":"832bc6a.a1a9e38","type":"ui_button","z":"fb1f9786.895398","d":true,"name":"","group":"1060b50f.fefd2b","order":4,"width":"6","height":"1","passthru":true,"label":"Good bye.","tooltip":"","color":"","bgcolor":"","icon":"","payload":"Good bye.","payloadType":"str","topic":"","x":310,"y":700,"wires":[["29948579.8865fa"]]},{"id":"29948579.8865fa","type":"link out","z":"fb1f9786.895398","name":"text out","links":["a118c2d8.975e"],"x":455,"y":700,"wires":[]},{"id":"1752586e.d190e8","type":"inject","z":"fb1f9786.895398","name":"","repeat":"","crontab":"","once":false,"onceDelay":0.1,"topic":"","payload":"","payloadType":"date","x":120,"y":700,"wires":[["832bc6a.a1a9e38"]]},{"id":"8f389964.6d7d88","type":"ui_button","z":"fb1f9786.895398","d":true,"name":"","group":"1060b50f.fefd2b","order":5,"width":"6","height":"1","passthru":true,"label":"Thank you.","tooltip":"","color":"","bgcolor":"","icon":"","payload":"Thank you.","payloadType":"str","topic":"","x":310,"y":740,"wires":[["cb4c72a6.82b3"]]},{"id":"cb4c72a6.82b3","type":"link out","z":"fb1f9786.895398","name":"text out","links":["a118c2d8.975e"],"x":455,"y":740,"wires":[]},{"id":"7f259077.238de","type":"inject","z":"fb1f9786.895398","name":"","props":[{"p":"payload","v":"","vt":"date"},{"p":"topic","v":"","vt":"string"}],"repeat":"","crontab":"","once":false,"onceDelay":0.1,"topic":"","payload":"","payloadType":"date","x":120,"y":740,"wires":[["8f389964.6d7d88"]]},{"id":"b30e920f.1b475","type":"ui_button","z":"fb1f9786.895398","d":true,"name":"","group":"1060b50f.fefd2b","order":6,"width":"6","height":"1","passthru":true,"label":"I don't know.","tooltip":"","color":"","bgcolor":"","icon":"","payload":"I don't know.","payloadType":"str","topic":"","x":310,"y":780,"wires":[["48ad5509.c3b53c"]]},{"id":"48ad5509.c3b53c","type":"link out","z":"fb1f9786.895398","name":"text out","links":["a118c2d8.975e"],"x":455,"y":780,"wires":[]},{"id":"913bfad5.9f4428","type":"inject","z":"fb1f9786.895398","name":"","repeat":"","crontab":"","once":false,"onceDelay":0.1,"topic":"","payload":"","payloadType":"date","x":120,"y":780,"wires":[["b30e920f.1b475"]]},{"id":"23b641f5.1d4f3e","type":"ui_button","z":"fb1f9786.895398","name":"","group":"1060b50f.fefd2b","order":7,"width":"3","height":"1","passthru":true,"label":"Yes.","color":"","bgcolor":"","icon":"","payload":"Yes.","payloadType":"str","topic":"","x":290,"y":340,"wires":[["1cf0335d.deb22d"]]},{"id":"1cf0335d.deb22d","type":"link out","z":"fb1f9786.895398","name":"text out","links":["a118c2d8.975e"],"x":455,"y":340,"wires":[]},{"id":"e0b67bbf.ff76e8","type":"inject","z":"fb1f9786.895398","name":"","repeat":"","crontab":"","once":false,"onceDelay":0.1,"topic":"","payload":"","payloadType":"date","x":120,"y":340,"wires":[["23b641f5.1d4f3e"]]},{"id":"fe604004.4e8db","type":"ui_button","z":"fb1f9786.895398","name":"","group":"1060b50f.fefd2b","order":8,"width":"3","height":"1","passthru":true,"label":"No.","color":"","bgcolor":"","icon":"","payload":"No.","payloadType":"str","topic":"","x":290,"y":380,"wires":[["ab49a76b.93dd58"]]},{"id":"ab49a76b.93dd58","type":"link out","z":"fb1f9786.895398","name":"text out","links":["a118c2d8.975e"],"x":455,"y":380,"wires":[]},{"id":"5fe8e816.226298","type":"inject","z":"fb1f9786.895398","name":"","repeat":"","crontab":"","once":false,"onceDelay":0.1,"topic":"","payload":"","payloadType":"date","x":120,"y":380,"wires":[["fe604004.4e8db"]]},{"id":"1060b50f.fefd2b","type":"ui_group","z":"","name":"TTS - Text to Speech","tab":"59755ac7.37f3d4","order":1,"disp":true,"width":"6","collapse":false},{"id":"59755ac7.37f3d4","type":"ui_tab","z":"","name":"TTS","icon":"dashboard","order":3,"disabled":false,"hidden":false}]